{
  "mission_logs": [
    {
      "time": "12:11:34",
      "source": "QUEEN",
      "message": "Connected to AirSim",
      "level": "INFO"
    },
    {
      "time": "12:11:34",
      "source": "QUEEN",
      "message": "Initializing - COMMAND CENTER MODE",
      "level": "INFO"
    },
    {
      "time": "12:11:34",
      "source": "QUEEN",
      "message": "Starting",
      "level": "INFO"
    },
    {
      "time": "12:11:36",
      "source": "WARRIOR",
      "message": "Initializing",
      "level": "INFO"
    },
    {
      "time": "12:11:36",
      "source": "WARRIOR",
      "message": "\ud83c\udfaf PATROL CHANGE: (0.0, 0.0) R=30.0",
      "level": "WARNING"
    },
    {
      "time": "12:11:36",
      "source": "WARRIOR",
      "message": "\u2192 (30.0, 0.0)",
      "level": "INFO"
    },
    {
      "time": "12:11:36",
      "source": "WARRIOR",
      "message": "Move error: Future.join() takes 1 positional argument but 2 were given",
      "level": "WARNING"
    },
    {
      "time": "12:11:38",
      "source": "QUEEN",
      "message": "\u2708\ufe0f Airborne - Command Center",
      "level": "INFO"
    },
    {
      "time": "12:11:38",
      "source": "KAMIKAZE",
      "message": "Initializing",
      "level": "INFO"
    },
    {
      "time": "12:11:39",
      "source": "WARRIOR",
      "message": "\u2192 (15.0, 26.0)",
      "level": "INFO"
    },
    {
      "time": "12:11:39",
      "source": "WARRIOR",
      "message": "Move error: Future.join() takes 1 positional argument but 2 were given",
      "level": "WARNING"
    },
    {
      "time": "12:11:40",
      "source": "WARRIOR",
      "message": "Pos: (19.6, 2.5, -11.4)",
      "level": "INFO"
    },
    {
      "time": "12:11:42",
      "source": "QUEEN",
      "message": "\ud83d\udce1 Monitoring Warrior camera feed",
      "level": "WARNING"
    },
    {
      "time": "12:11:42",
      "source": "QUEEN",
      "message": "\ud83d\udce5 Initializing AI model (may take a moment)...",
      "level": "INFO"
    },
    {
      "time": "12:11:42",
      "source": "WARRIOR",
      "message": "\u2192 (-15.0, 26.0)",
      "level": "INFO"
    },
    {
      "time": "12:11:42",
      "source": "WARRIOR",
      "message": "Move error: Future.join() takes 1 positional argument but 2 were given",
      "level": "WARNING"
    },
    {
      "time": "12:11:45",
      "source": "WARRIOR",
      "message": "\u2192 (-30.0, 0.0)",
      "level": "INFO"
    },
    {
      "time": "12:11:46",
      "source": "WARRIOR",
      "message": "Move error: Future.join() takes 1 positional argument but 2 were given",
      "level": "WARNING"
    },
    {
      "time": "12:11:46",
      "source": "WARRIOR",
      "message": "Pos: (-3.3, 22.0, -14.9)",
      "level": "INFO"
    },
    {
      "time": "12:11:46",
      "source": "QUEEN",
      "message": "\u2705 AI model ready",
      "level": "INFO"
    }
  ],
  "patrol_center_x": 0,
  "patrol_center_y": 0,
  "patrol_radius": 30,
  "patrol_relative_to_queen": false
}